{
  "multipart": [
     {
    "apply":{
      "model":"minecraft:block/stone/stone_brick_wall_post_pillar"
       },
    "when" : {
      "up":"true","north":"none","south":"none","east":"none","west":"none"
       }
     },
     {
        "apply": {
          "model": "minecraft:block/stone/stone_brick_wall_post_pillar"
        },
        "when": {"OR":[
          {"up": "true","north":"low|tall"},
          {"up": "true","south":"low|tall"},
          {"up": "true","east":"low|tall"},
          {"up": "true","west":"low|tall"}
        ]}
     },
     {
        "apply": {
          "model": "minecraft:block/stone/stone_brick_wall_post_low"
        },
        "when": {
          "north":"low","south":"low","east":"low","west":"low"
        }
     },
     {
      "apply": {
        "model": "minecraft:block/stone/stone_brick_wall_post"
      },
      "when": {
        "north":"tall","south":"tall","east":"tall","west":"tall"
      }
     },
      {
        "apply": {
          "model": "minecraft:block/stone/stone_brick_wall_ns",
          "uvlock": true
        },
        "when": {
          "north": "low"
        }
      },
      {
        "apply": {
          "model": "minecraft:block/stone/stone_brick_wall_ns",
          "uvlock": true,
          "y": 180
        },
        "when": {
          "south": "low"
        }
      },
      {
        "apply": {
          "model": "minecraft:block/stone/stone_brick_wall_ew",
          "uvlock": true
        },
        "when": {
          "east": "low"
        }
      },
      {
        "apply": {
          "model": "minecraft:block/stone/stone_brick_wall_ew",
          "uvlock": true,
          "y": 180
        },
        "when": {
          "west": "low"
        }
      },
      {
        "apply": {
          "model": "minecraft:block/stone/stone_brick_wall_ns_tall",
          "uvlock": true
        },
        "when": {
          "north": "tall"
        }
      },
      {
        "apply": {
          "model": "minecraft:block/stone/stone_brick_wall_ns_tall",
          "uvlock": true,
          "y": 180
        },
        "when": {
          "south": "tall"
        }
      },
      {
        "apply": {
          "model": "minecraft:block/stone/stone_brick_wall_ew_tall",
          "uvlock": true,
          "y":0
        },
        "when": {
          "east": "tall"
        }
      },
      {
        "apply": {
          "model": "minecraft:block/stone/stone_brick_wall_ew_tall",
          "uvlock": true,
          "y": 180
        },
        "when": {
          "west": "tall"
        }
      }
  ]
}